cupynumeric/__init__.py
cupynumeric/_version.py
cupynumeric/_version.py.bak
cupynumeric/config.py
cupynumeric/install_info.py
cupynumeric/install_info.py.in
cupynumeric/install_info.pyi
cupynumeric/patch.py
cupynumeric/py.typed
cupynumeric/runtime.py
cupynumeric/settings.py
cupynumeric/types.py
cupynumeric/_array/__init__.py
cupynumeric/_array/array.py
cupynumeric/_array/doctor.py
cupynumeric/_array/flags.py
cupynumeric/_array/thunk.py
cupynumeric/_array/util.py
cupynumeric/_dlpack/__init__.py
cupynumeric/_module/__init__.py
cupynumeric/_module/_unary_red_utils.py
cupynumeric/_module/array_basic.py
cupynumeric/_module/array_delete.py
cupynumeric/_module/array_dimension.py
cupynumeric/_module/array_joining.py
cupynumeric/_module/array_rearrange.py
cupynumeric/_module/array_shape.py
cupynumeric/_module/array_splitting.py
cupynumeric/_module/array_tiling.py
cupynumeric/_module/array_transpose.py
cupynumeric/_module/binary_bit_packing.py
cupynumeric/_module/creation_data.py
cupynumeric/_module/creation_matrices.py
cupynumeric/_module/creation_ranges.py
cupynumeric/_module/creation_shape.py
cupynumeric/_module/indexing.py
cupynumeric/_module/io_numpy.py
cupynumeric/_module/linalg_mvp.py
cupynumeric/_module/logic_array_contents.py
cupynumeric/_module/logic_array_type.py
cupynumeric/_module/logic_comparison.py
cupynumeric/_module/logic_truth.py
cupynumeric/_module/math_complex.py
cupynumeric/_module/math_extrema.py
cupynumeric/_module/math_misc.py
cupynumeric/_module/math_rounding.py
cupynumeric/_module/math_sum_prod_diff.py
cupynumeric/_module/sets_making.py
cupynumeric/_module/ssc_counting.py
cupynumeric/_module/ssc_searching.py
cupynumeric/_module/ssc_sorting.py
cupynumeric/_module/stats_avgs_vars.py
cupynumeric/_module/stats_correlating.py
cupynumeric/_module/stats_histograms.py
cupynumeric/_module/stats_order.py
cupynumeric/_module/window.py
cupynumeric/_sphinxext/__init__.py
nvidia_cupynumeric-26.1.0.dist-info/METADATA
nvidia_cupynumeric-26.1.0.dist-info/WHEEL
nvidia_cupynumeric-26.1.0.dist-info/entry_points.txt
nvidia_cupynumeric-26.1.0.dist-info/RECORD
