Metadata-Version: 2.2
Name: nvidia-cupynumeric
Version: 26.1.0
Summary: cuPyNumeric - NumPy and SciPy on Multi-Node Multi-GPU systems
Author: NVIDIA Corporation
License: Apache-2.0
Classifier: Intended Audience :: Developers
Classifier: Topic :: Database
Classifier: Topic :: Scientific/Engineering
Classifier: License :: OSI Approved :: Apache Software License
Classifier: Programming Language :: Python
Classifier: Programming Language :: Python :: 3.11
Classifier: Programming Language :: Python :: 3.12
Classifier: Programming Language :: Python :: 3.13
Project-URL: homepage, https://github.com/nv-legate/cupynumeric
Requires-Python: >=3.11
Requires-Dist: numpy!=2.1.0,<2.4.0,>=1.22
Requires-Dist: cffi
Requires-Dist: opt_einsum
Requires-Dist: legate==26.01.*,>=0.0.0a0
Requires-Dist: cutensor-cu12<2.3.0.6,>=2.0; sys_platform == "linux"
Requires-Dist: nvidia-cublas-cu12; sys_platform == "linux"
Requires-Dist: nvidia-cufft-cu12; sys_platform == "linux"
Requires-Dist: nvidia-cusolver-cu12; sys_platform == "linux"
Requires-Dist: nvidia-cusparse-cu12; sys_platform == "linux"
Requires-Dist: nvidia-nvjitlink-cu12; sys_platform == "linux"
